Metadata-Version: 2.1
Name: TOPSIS-ANKITA-101903766
Version: 1.0
Summary: It's a package that calcuates Topsis score and ranks accordingly
Home-page: https://github.com/ankitapuri/Topsis-Ankita-101903766
Author: AnkitaPuri
Author-email: puriankita30@gmail.com
License: MIT
Platform: UNKNOWN
Classifier: Programming Language :: Python :: 3
Classifier: License :: OSI Approved :: MIT License
Classifier: Operating System :: OS Independent
License-File: LICENSE
